DynamicRoutingUpdater/AddressInfo.py
DynamicRoutingUpdater/DynamicRoutingUpdater.py
DynamicRoutingUpdater/NetworkAdapter.py
DynamicRoutingUpdater/NetworkHookHandler.py
DynamicRoutingUpdater/NetworkInfoWatcher.py
DynamicRoutingUpdater/RouteAndRuleObserver.py
DynamicRoutingUpdater/Routing.py
DynamicRoutingUpdater/RoutingTable.py
DynamicRoutingUpdater/Rules.py
DynamicRoutingUpdater/__init__.py
DynamicRoutingUpdater/objects.py
DynamicRoutingUpdater/version.py
pyDynamicRoutingUpdater-0.0.8.dist-info/LICENSE
pyDynamicRoutingUpdater-0.0.8.dist-info/METADATA
pyDynamicRoutingUpdater-0.0.8.dist-info/WHEEL
pyDynamicRoutingUpdater-0.0.8.dist-info/top_level.txt
pyDynamicRoutingUpdater-0.0.8.dist-info/RECORD
