Metadata-Version: 2.1
Name: pyDynamicRoutingUpdater
Version: 0.0.8
Summary: A Python library to modify and alter the routing table in according to configuration passed
Home-page: https://github.com/iktdev-no/DynamicRoutingUpdater
Author: Brage Skjønborg
Author-email: bskjon@outlook.com
Classifier: Intended Audience :: Developers
Classifier: Operating System :: POSIX :: Linux
Classifier: Programming Language :: Python
Classifier: Programming Language :: Python :: 3
Classifier: Topic :: System :: Networking
Classifier: Topic :: Software Development :: Libraries :: Python Modules
Requires-Python: >=3.9.0
License-File: LICENSE
Requires-Dist: netifaces >=0.11.0
Requires-Dist: netaddr >=0.8.0
